{
  "add_target_extension": {
    "dynamic": "exe", 
    "static": "exe"
  }, 
  "build_scripts_uoa": [
    "9738ca3d2555f6eb"
  ], 
  "run_cmds": {
    "default": {
      "dataset_classes_uoa": [
        "183d8d1e484b95fa"
      ], 
      "hot_functions": [
        {
          "percent": "90", 
          "name": "matmul"
        }
      ], 
      "run_time": {
        "run_cmd_out1": "tmp-output1.tmp", 
        "run_cmd_out2": "tmp-output2.tmp", 
        "run_correctness_output_files": [
          "tmp-output.tmp", 
          "tmp-output2.tmp"
        ], 
        "run_input_files": [
          "data"
        ], 
        "run_output_files": [
          "tmp-output.tmp"
        ]
      }
    }
  }, 
  "main_language": "fortran", 
  "clean_scripts_names": {
    "clean": "Universal cleaning"
  }, 
  "cm_classes_uoa": [
    "28ecc0c2a0215b5b", 
    "99ebfa96846f4bc8", 
    "1a8b0e537d8566d6"
  ], 
  "run_vars_desc": {
    "##CT_REPEAT_MAIN": {
      "default_value": "1", 
      "field_size": "7", 
      "skip_form_refresh": "yes", 
      "explore_stop": "1000000", 
      "forbid_disable_at_random": "yes", 
      "desc_text": "Main function/kernel repetition", 
      "explore_level": "1", 
      "property": "yes", 
      "explorable": "yes", 
      "explore_start": "0", 
      "explore_step": "10", 
      "sort_index": "1", 
      "type": "integer"
    }
  }, 
  "run_vars": {
    "CT_REPEAT_MAIN": "1", 
    "CT_MATRIX_DIMENSION": "512"
  }, 
  "target_file": "a", 
  "cm_build_dependencies": [], 
  "source_files": [
    "matmul.F"
  ], 
  "source_files_templates": [
    "matmul.F"
  ], 
  "build_scripts_names": {
    "dynamic": {
      "build_dynamic_bin_f": "Build dynamic binary directly"
    }, 
    "static": {
      "build_static_bin_f": "Build static binary directly"
    }
  }, 
  "tags": [
    "program", 
    "demo"
  ], 
  "build_compiler_vars_desc": {
    "##N": {
      "default_value": "256", 
      "field_size": "7", 
      "skip_form_refresh": "yes", 
      "explore_stop": "5000", 
      "forbid_disable_at_random": "yes", 
      "dataset_size": "yes", 
      "desc_text": "Dataset: Matrix size N", 
      "explore_level": "1", 
      "property": "yes", 
      "explorable": "yes", 
      "explore_start": "2", 
      "explore_step": "1", 
      "sort_index": "2", 
      "type": "integer"
    }
  }
}